bankroll/brokers/vanguard/__init__.py
bankroll/brokers/vanguard/account.py
bankroll/brokers/vanguard/py.typed
bankroll_broker_vanguard-0.4.0.dist-info/LICENSE
bankroll_broker_vanguard-0.4.0.dist-info/METADATA
bankroll_broker_vanguard-0.4.0.dist-info/WHEEL
bankroll_broker_vanguard-0.4.0.dist-info/top_level.txt
bankroll_broker_vanguard-0.4.0.dist-info/RECORD
