Metadata-Version: 2.1
Name: bankroll-broker-vanguard
Version: 0.4.0
Summary: Vanguard support for bankroll (experimental)
Home-page: https://github.com/bankroll-py/bankroll-broker-vanguard
Author: Justin Spahr-Summers
Author-email: justin@jspahrsummers.com
License: MIT
Keywords: trading investing finance portfolio vanguard
Platform: UNKNOWN
Classifier: Development Status :: 2 - Pre-Alpha
Classifier: Intended Audience :: Developers
Classifier: License :: OSI Approved :: MIT License
Classifier: Operating System :: OS Independent
Classifier: Programming Language :: Python :: 3 :: Only
Classifier: Programming Language :: Python :: 3.7
Classifier: Programming Language :: Python :: 3
Classifier: Topic :: Office/Business :: Financial :: Investment
Classifier: Typing :: Typed
Requires-Dist: bankroll-broker (~=0.4.0)
Requires-Dist: bankroll-model (~=0.4.0)
